usb2container
